foursquare/data_sdk/__init__.py
foursquare/data_sdk/__main__.py
foursquare/data_sdk/_query.py
foursquare/data_sdk/auth.py
foursquare/data_sdk/cli.py
foursquare/data_sdk/data_sdk.py
foursquare/data_sdk/enums.py
foursquare/data_sdk/environment.py
foursquare/data_sdk/errors.py
foursquare/data_sdk/models.py
foursquare/data_sdk/py.typed
foursquare/data_sdk/types.py
foursquare/data_sdk/utils.py
foursquare.data_sdk-1.0.1.dist-info/entry_points.txt
foursquare.data_sdk-1.0.1.dist-info/WHEEL
foursquare.data_sdk-1.0.1.dist-info/METADATA
foursquare.data_sdk-1.0.1.dist-info/RECORD
